{
  "Element": "Earth",
  "BaseHP": 8.0,
  "BaseWeight": 90,
  "Affinity": {
    "HP": 0.9,
    "Strength": 0.7,
    "Magic": 0.4,
    "Wisdom": 0.2,
    "Speed": 0.5
  },
  "Techs": [
    {
      "Tech": "Claw",
      "Level": 1
    },
    {
      "Tech": "DirtRow",
      "Level": 2
    },
    {
      "Tech": "Pitfall",
      "Level": 4
    },
    {
      "Tech": "EarthDrill",
      "Level": 7
    }
  ],
  "Evolutions": [
    {
      "Species": "Molinee",
      "Level": 10,
      "Strength": {
        "min": -1,
        "max": 14
      },
      "Weight": {
        "min": -1,
        "max": 149
      }
    },
    {
      "Species": "Molarth",
      "Level": 10,
      "Strength": {
        "min": 15,
        "max": 999999
      },
      "Weight": {
        "min": 150,
        "max": 999999
      }
    }
  ],
  "BaseAncestor": "Molun",
  "Diet": "Omnivore",
  "Class": "Bear",
  "Behavior": "Stationary",
  "Drops": [
    {
      "Item": "Rock",
      "Chance": 0.2
    }
  ],
  "Name": null,
  "FavoriteItem": "Rock",
  "Passive": "Fracture",
  "EXPCurve": "Easy",
  "Spot": "BinaryForest"
}
